mezzanine_cartridge_api/__init__.py
mezzanine_cartridge_api/apps.py
mezzanine_cartridge_api/serializers.py
mezzanine_cartridge_api/settings.py
mezzanine_cartridge_api/urls.py
mezzanine_cartridge_api/views.py
mezzanine_cartridge_api/templates/rest_framework_swagger/http.html
mezzanine_cartridge_api/templates/rest_framework_swagger/https.html
mezzanine_cartridge_api-1.0.1.data/data/templates/http.html
mezzanine_cartridge_api-1.0.1.data/data/templates/https.html
mezzanine_cartridge_api-1.0.1.dist-info/METADATA
mezzanine_cartridge_api-1.0.1.dist-info/WHEEL
mezzanine_cartridge_api-1.0.1.dist-info/top_level.txt
mezzanine_cartridge_api-1.0.1.dist-info/RECORD
