Metadata-Version: 2.1
Name: mezzanine-cartridge-api
Version: 1.0.1
Summary: A REST Web API for Mezzanine CMS with the Cartridge e-commerce extension
Home-page: https://github.com/jackvz/mezzanine-cartridge-api
Author: Jack van Zyl
Author-email: jackvanzyl@icloud.com
License: UNKNOWN
Platform: UNKNOWN
Classifier: Programming Language :: Python :: 3
Classifier: License :: OSI Approved :: MIT License
Classifier: Operating System :: OS Independent
Requires-Dist: django-custom-settings (==0.1.4)
Requires-Dist: django-oauth-toolkit (==1.1.1)
Requires-Dist: django-cors-middleware (==1.3.1)
Requires-Dist: djangorestframework (==3.9.2)
Requires-Dist: djangorestframework-api-key (==0.3.1)
Requires-Dist: django-rest-swagger (==2.2.0)
